<?xml version="1.0" ?>

<Wizard>
<!-- Definition file for Tag based JSP Web application -->
<WizardTask class="oracle.jbo.dt.ui.wizards.wiztemplate.input.StaticProperties">
    <config>
    </config>
    <wizdata>
        <Property name="HTML_ROOT_DIR"></Property>
        <Property name="HTML_SRC_DIR"></Property>
        <Property name="charset"></Property>
    </wizdata>
</WizardTask>

   <WizardTask class="oracle.jbo.dt.ui.wizards.tagswebapp.CheckForBC4JProjectsTask" />
   <WizardTask class="oracle.jbo.dt.ui.wizards.wiztemplate.ui.UIWizardSequencer">
      <config>
         <!-- this is displayed as wizard image -->
         <ImageFileName>/oracle/jbo/dt/ui/wizards/tagswebapp/appmgr.gif</ImageFileName>
         <!-- Used as the title in the wizard dialog -->
         <WizardDialogTitle translateable="true">UIX_JSP_TITLE_WIZARD</WizardDialogTitle>
         <!-- resource retrieved from this bundle, more than one bundle can be specified -->
         <UIResourceBundle name="res" properties="def/cabotagswebapp/webapp.rts"/>
      </config>
      <wizdata>
         <WelcomePanel>
               <PanelTitle translateable="true">WELCOME_PAGE_TITLE</PanelTitle>
               <BoldText translateable="true">WELCOME_TITLE_TEXT</BoldText>
               <description translateable="true">WELCOME_TEXT</description>
               <JDeveloperHelpUrl>f1_jspuixappwelcome_html</JDeveloperHelpUrl>
               <WelcomePageId>CaboTagsWebApp</WelcomePageId>
         </WelcomePanel>

         <UIPanel class="oracle.jbo.dt.common.wizard.DataDefinitionSelectionPanel"/>
         <UIPanel class="oracle.jbo.dt.ui.wizards.tagswebapp.ViewsPanel"/>
         <UIPanel class="oracle.jbo.dt.ui.wizards.tagswebapp.ViewLinkPanel"/>
         <UIPanel class="oracle.jbo.dt.ui.wizards.tagswebapp.FinishPanel"/>

         <PanelSettings>
            <PanelData panelclass="oracle.jbo.dt.ui.wizards.tagswebapp.ViewsPanel">
               <PanelTitle translateable="true">TITLE_VIEW_SELECTION</PanelTitle>
               <JDeveloperHelpUrl>f1_jspuixappviewform_html</JDeveloperHelpUrl>
               <PROMPT_GEN_PAGE translateable="true">PROMPT_GEN_PAGE</PROMPT_GEN_PAGE>
               <TITLE_VO translateable="true">TITLE_VO</TITLE_VO>
               <VIEWS_PANEL_DESCRIPTION translateable="true" >VIEWS_PANEL_DESCRIPTION</VIEWS_PANEL_DESCRIPTION>
               <TITLE_FORM_OPTIONS translateable="true">TITLE_FORM_OPTIONS</TITLE_FORM_OPTIONS>
               <TITLE_QUERY_FORM translateable="true">TITLE_QUERY_FORM</TITLE_QUERY_FORM>
               <TITLE_BROWSE_FORM translateable="true">TITLE_BROWSE_FORM</TITLE_BROWSE_FORM>
               <TITLE_EDIT_FORM translateable="true">TITLE_EDIT_FORM</TITLE_EDIT_FORM>
               <TITLE_VIEW_SELECTION translateable="true">TITLE_VIEW_SELECTION</TITLE_VIEW_SELECTION>
               <VIEW_PANEL_FILE_NAME translateable="true">VIEW_PANEL_FILE_NAME</VIEW_PANEL_FILE_NAME>
            </PanelData>
            <PanelData panelclass="oracle.jbo.dt.common.wizard.DataDefinitionSelectionPanel">
               <PanelTitle translateable="true">DATADEF_PAGE_TITLE</PanelTitle>
               <SELECT_DATADEFINITION translateable="true">SELECT_DATADEFINITION_PROMPT</SELECT_DATADEFINITION>
               <NEW_DATADEFINITION translateable="true">NEW_DATADEFINITION</NEW_DATADEFINITION>
               <SELECT_APPMODULE translateable="true">SELECT_APPMODULE</SELECT_APPMODULE>
               <SELECT_DATADEF_INTRO translateable="true">SELECT_DATADEF_INTRO</SELECT_DATADEF_INTRO>
               <SELECTED_MODEL translateable="true">SELECTED_MODEL</SELECTED_MODEL>
               <JDeveloperHelpUrl>f1_jspuixappdatamodel_html</JDeveloperHelpUrl>
            </PanelData>
            <PanelData panelclass="oracle.jbo.dt.ui.wizards.tagswebapp.ViewLinkPanel">
               <PanelTitle translateable="true">VIEWLINK_PANEL_TITLE</PanelTitle>
               <JDeveloperHelpUrl>f1_jspuixappviewlinks_html</JDeveloperHelpUrl>
               <VIEWLINK_PANEL_TITLE translateable="true">VIEWLINK_PANEL_TITLE</VIEWLINK_PANEL_TITLE>
            </PanelData>
            <PanelData panelclass="oracle.jbo.dt.ui.wizards.tagswebapp.FinishPanel">
               <PanelTitle translateable="true">FINISH_PAGE_TITLE</PanelTitle>
               <JDeveloperHelpUrl>f1_jspuixappfinish_html</JDeveloperHelpUrl>
               <FINISH_PAGE_TITLE translateable="true">FINISH_PAGE_TITLE</FINISH_PAGE_TITLE>
               <FINISH_SUMMARY translateable="true">FINISH_SUMMARY</FINISH_SUMMARY>
               <FINISH_TEXT translateable="true">FINISH_TEXT</FINISH_TEXT>
            </PanelData>
         </PanelSettings>
      </wizdata>
   </WizardTask>

   <WizardTask class="oracle.jbo.dt.ui.wizards.tagswebapp.WebAppWizardCodeGenerationTask">
   </WizardTask>


<WizardTask class="oracle.jbo.dt.ui.wizards.wiztemplate.codegen.FileCodeGenerator">
    <config/>

    <wizdata>
                <selection id="Common">
                        <file in="blafjspwebapp/uix_errorpage.jsp" action="substitute"
                                                   out="{%HTML_SRC_DIR%}/errorpage.jsp" />
                        <file in="blafjspwebapp/main.jsp" action="substitute"
                              out="{%HTML_SRC_DIR%}/main.jsp" runnableTarget="true" openInEditor="true"/>
			      
                        <file in="blafjspwebapp/HelpPage.jsp" action="substitute"
                                                   out="{%HTML_SRC_DIR%}/main_Help.jsp" />
                        <file in="blafjspwebapp/GlobalDefs.jsp" action="substitute"
                                                   out="{%HTML_SRC_DIR%}/GlobalDefs.jsp"/>
                         <file in="common/tagcomp/DataHandlerComponent.jsp" action="copy"
                               out="{%HTML_SRC_DIR%}/DataHandlerComponent.jsp" overwrite="yes"/>
                        <file in="common/misc/globalinclude.html" action="substitute"
                                                   out="{%HTML_SRC_DIR%}/globalinclude.html" overwrite="prompt"  />
                        <file in="common/misc/ojsp-global-include.xml" action="substitute"
                                                   out="{%HTML_SRC_DIR%}/WEB-INF/ojsp-global-include.xml" overwrite="prompt"  />
                        <file in="common/uix-config.xml" action="substitute"
                                                   out="{%HTML_SRC_DIR%}/WEB-INF/uix-config.xml" overwrite="prompt"  />
                        <configureproject configurer="oracle.jbo.dt.jsp.configurers.UIXTagsProject" />
                </selection>


                <selection id="Association">
                      <file in="blafjspwebapp/HelpPage.jsp" action="substitute"
                                out="{%HTML_SRC_DIR%}/{%MasterViewFileBaseName%}_Help.jsp" />
				
                      <file in="blafjspwebapp/UixEdit.jsp" action="substitute"
                               out="{%HTML_SRC_DIR%}/{%MasterViewFileBaseName%}_Edit.jsp" />
			       
                      <file in="blafjspwebapp/AssociationPage.jsp" action="substitute"
                               out="{%HTML_SRC_DIR%}/{%AssociationFileBaseName%}_Browse.jsp" />
                </selection>

	              


                <selection id="InsertRecordForm">
                </selection>

                <selection id="BrowseOnlyForm">
		
                        <file in="blafjspwebapp/HelpPage.jsp" action="substitute"
                                out="{%HTML_SRC_DIR%}/{%ViewFileBaseName%}_Help.jsp" overwrite="yes"/>
				
                        <file in="blafjspwebapp/UixEdit.jsp" action="substitute"
                               out="{%HTML_SRC_DIR%}/{%ViewFileBaseName%}_Edit.jsp" overwrite="yes"/>
			       
                        <file in="blafjspwebapp/UixBrowseEdit.jsp" action="substitute"
                              out="{%HTML_SRC_DIR%}/{%ViewFileBaseName%}_Browse.jsp"/>
                </selection>

                <selection id="EditForm">
                </selection>

                <selection id="QueryForm">
                </selection>

                <selection id="ViewMenu">
                </selection>
   </wizdata>
</WizardTask>

</Wizard>
